README.md
setup.py
deep_serverless/__init__.py
deep_serverless.egg-info/PKG-INFO
deep_serverless.egg-info/SOURCES.txt
deep_serverless.egg-info/dependency_links.txt
deep_serverless.egg-info/not-zip-safe
deep_serverless.egg-info/requires.txt
deep_serverless.egg-info/top_level.txt
deep_serverless/models/__init__.py
deep_serverless/models/base.py
deep_serverless/models/source_extract.py
deep_serverless/utils/__init__.py
deep_serverless/utils/camelize.py
deep_serverless/utils/common.py
deep_serverless/utils/date_extractor.py
deep_serverless/utils/decorators.py
deep_serverless/utils/s3.py
deep_serverless/utils/sentry.py
deep_serverless/utils/tests.py
deep_serverless/utils/validators.py
deep_serverless/utils/django_utils/__init__.py
deep_serverless/utils/django_utils/common.py
deep_serverless/utils/django_utils/file.py