Metadata-Version: 2.1
Name: deep-serverless
Version: 1.0.4
Summary: Sharable modules from Deep serverlss
Home-page: https://github.com/the-deep/serverless
Author: TC Dev
Author-email: dev@togglecorp.com
License: MIT
Platform: UNKNOWN
Classifier: License :: OSI Approved :: MIT License
Classifier: Programming Language :: Python :: 3
Classifier: Topic :: Utilities
Classifier: Operating System :: OS Independent
